ebix/__init__.py
ebix/cli.py
ebix/commands/__init__.py
ebix/commands/init_command.py
ebix/templates/backend/django/mydjango/manage.py
ebix/templates/backend/django/mydjango/mydjango/__init__.py
ebix/templates/backend/django/mydjango/mydjango/asgi.py
ebix/templates/backend/django/mydjango/mydjango/settings.py
ebix/templates/backend/django/mydjango/mydjango/urls.py
ebix/templates/backend/django/mydjango/mydjango/wsgi.py
ebix/templates/backend/fastapi/README.md
ebix/templates/backend/fastapi/main.py
ebix/templates/backend/fastapi/requirements.txt
ebix/templates/backend/flask/app.py
ebix/templates/backend/flask/requirements.txt
ebix/templates/backend/node/package-lock.json
ebix/templates/backend/node/package.json
ebix/templates/backend/node/node_modules/.package-lock.json
ebix/templates/backend/node/node_modules/accepts/HISTORY.md
ebix/templates/backend/node/node_modules/accepts/README.md
ebix/templates/backend/node/node_modules/accepts/package.json
ebix/templates/backend/node/node_modules/body-parser/HISTORY.md
ebix/templates/backend/node/node_modules/body-parser/README.md
ebix/templates/backend/node/node_modules/body-parser/package.json
ebix/templates/backend/node/node_modules/bytes/History.md
ebix/templates/backend/node/node_modules/bytes/Readme.md
ebix/templates/backend/node/node_modules/bytes/package.json
ebix/templates/backend/node/node_modules/call-bind-apply-helpers/CHANGELOG.md
ebix/templates/backend/node/node_modules/call-bind-apply-helpers/README.md
ebix/templates/backend/node/node_modules/call-bind-apply-helpers/package.json
ebix/templates/backend/node/node_modules/call-bind-apply-helpers/tsconfig.json
ebix/templates/backend/node/node_modules/call-bound/CHANGELOG.md
ebix/templates/backend/node/node_modules/call-bound/README.md
ebix/templates/backend/node/node_modules/call-bound/package.json
ebix/templates/backend/node/node_modules/call-bound/tsconfig.json
ebix/templates/backend/node/node_modules/content-disposition/HISTORY.md
ebix-0.3.dist-info/METADATA
ebix-0.3.dist-info/WHEEL
ebix-0.3.dist-info/entry_points.txt
ebix-0.3.dist-info/top_level.txt
ebix-0.3.dist-info/RECORD
