Metadata-Version: 2.1
Name: ebix
Version: 0.3
Requires-Dist: click
Requires-Dist: questionary
